ical_library/__init__.py
ical_library/cache_client.py
ical_library/client.py
ical_library/exceptions.py
ical_library/py.typed
ical_library/timeline.py
ical_library/base_classes/__init__.py
ical_library/base_classes/base_class.py
ical_library/base_classes/component.py
ical_library/base_classes/property.py
ical_library/help_modules/__init__.py
ical_library/help_modules/component_context.py
ical_library/help_modules/dt_utils.py
ical_library/help_modules/lru_cache.py
ical_library/help_modules/property_utils.py
ical_library/help_modules/timespan.py
ical_library/ical_components/__init__.py
ical_library/ical_components/abstract_components.py
ical_library/ical_components/v_alarm.py
ical_library/ical_components/v_calendar.py
ical_library/ical_components/v_event.py
ical_library/ical_components/v_free_busy.py
ical_library/ical_components/v_journal.py
ical_library/ical_components/v_timezone.py
ical_library/ical_components/v_todo.py
ical_library/ical_properties/__init__.py
ical_library/ical_properties/cal_address.py
ical_library/ical_properties/dt.py
ical_library/ical_properties/geo.py
ical_library/ical_properties/ical_duration.py
ical_library/ical_properties/ints.py
ical_library/ical_properties/pass_properties.py
ical_library/ical_properties/periods.py
ical_library/ical_properties/rrule.py
ical_library/ical_properties/trigger.py
ical_library/ical_properties/tz_offset.py
ical_library-0.2.3.dist-info/LICENSE
ical_library-0.2.3.dist-info/WHEEL
ical_library-0.2.3.dist-info/METADATA
ical_library-0.2.3.dist-info/RECORD
