Metadata-Version: 2.1
Name: ical-library
Version: 0.2.3
Summary: Fast, yet simple, iCalendar reader with excellent recurrence support.
Author-email: Jorrick Sleijster <jorricks3@gmail.com>
Requires-Python: >=3.8
Classifier: Intended Audience :: Information Technology
Classifier: Intended Audience :: Developers
Classifier: Operating System :: OS Independent
Classifier: Topic :: Communications
Classifier: Topic :: Communications :: Conferencing
Classifier: Topic :: Office/Business
Classifier: Topic :: Office/Business :: Office Suites
Classifier: Topic :: Internet
Classifier: Topic :: Software Development
Classifier: Topic :: Software Development :: Libraries
Classifier: Topic :: Software Development :: Libraries :: Python Modules
Classifier: Topic :: Software Development :: Libraries :: Application Frameworks
Classifier: Typing :: Typed
Classifier: License :: OSI Approved :: MIT License
Classifier: Development Status :: 4 - Beta
Classifier: Programming Language :: Python
Classifier: Programming Language :: Python :: 3
Classifier: Programming Language :: Python :: 3 :: Only
Classifier: Programming Language :: Python :: 3.8
Classifier: Programming Language :: Python :: 3.9
Classifier: Programming Language :: Python :: 3.10
Classifier: Programming Language :: Python :: 3.11
Classifier: Programming Language :: Python :: 3.12
Requires-Dist: pendulum>=2.0.0,<3.0.0
Requires-Dist: python-dateutil>=2.8.0
Requires-Dist: pre-commit >=2.19.0,<3.0.0 ; extra == "dev"
Requires-Dist: mkdocs >=1.3.0,<2.0.0 ; extra == "doc"
Requires-Dist: mkdocs-material >=8.3.9,<9.0.0 ; extra == "doc"
Requires-Dist: mkdocstrings[python] >=0.19.0,<1.0.0 ; extra == "doc"
Requires-Dist: termynal >=0.2.0,<1.0.0 ; extra == "doc"
Requires-Dist: pytest >=6.2.4,<7.0.0 ; extra == "test"
Requires-Dist: pytest-cov >=2.12.0,<4.0.0 ; extra == "test"
Requires-Dist: flake8 >=4.0.0,<5.0.0 ; extra == "test"
Requires-Dist: black >= 22.6.0,<23.0.0 ; extra == "test"
Requires-Dist: isort >=5.10.1,<6.0.0 ; extra == "test"
Requires-Dist: mypy ==0.910 ; extra == "test"
Requires-Dist: pytype >=2022.6.30 ; extra == "test"
Project-URL: Documentation, https://jorricks.github.io/iCal-library
Project-URL: Home, https://jorricks.github.io/iCal-library
Project-URL: Issues, https://github.com/Jorricks/iCal-library/issues
Project-URL: PullRequests, https://github.com/Jorricks/iCal-library/pulls
Project-URL: Source, https://github.com/Jorricks/iCal-library
Provides-Extra: dev
Provides-Extra: doc
Provides-Extra: test
